setup.py
wiki/__init__.py
wiki/client.py
wiki/functions.py
wiki/wiki_lexer.py
wiki_terminal.egg-info/PKG-INFO
wiki_terminal.egg-info/SOURCES.txt
wiki_terminal.egg-info/dependency_links.txt
wiki_terminal.egg-info/entry_points.txt
wiki_terminal.egg-info/not-zip-safe
wiki_terminal.egg-info/requires.txt
wiki_terminal.egg-info/top_level.txt