Metadata-Version: 1.1
Name: wiki-terminal
Version: 1.2.0
Summary: This script will enable you use wikipedia in terminal.
Home-page: https://github.com/JASON0916/wiki_terminal
Author: cm
Author-email: jason0916phoenix@gmail.com
License: MIT
Keywords: python wikipedia terminal
Platform: UNKNOWN
Classifier: Programming Language :: Python :: 2.7
